{
 "custom_fields": [
  {
   "_assign": null,
   "_comments": null,
   "_liked_by": null,
   "_user_tags": null,
   "allow_in_quick_entry": 0,
   "allow_on_submit": 0,
   "bold": 0,
   "collapsible": 0,
   "collapsible_depends_on": null,
   "columns": 0,
   "creation": "2022-08-31 01:14:55.213737",
   "default": null,
   "depends_on": null,
   "description": null,
   "docstatus": 0,
   "dt": "Sales Invoice Item",
   "fetch_from": "item_code.sub_group",
   "fetch_if_empty": 0,
   "fieldname": "sub_group",
   "fieldtype": "Link",
   "hidden": 0,
   "hide_border": 0,
   "hide_days": 0,
   "hide_seconds": 0,
   "idx": 14,
   "ignore_user_permissions": 0,
   "ignore_xss_filter": 0,
   "in_global_search": 0,
   "in_list_view": 0,
   "in_preview": 0,
   "in_standard_filter": 0,
   "insert_after": "item_group",
   "is_system_generated": 0,
   "is_virtual": 0,
   "label": "Sub Group",
   "length": 0,
   "mandatory_depends_on": null,
   "modified": "2022-08-31 01:14:55.213737",
   "modified_by": "Administrator",
   "module": null,
   "name": "Sales Invoice Item-sub_group",
   "no_copy": 0,
   "non_negative": 0,
   "options": "Item Group",
   "owner": "Administrator",
   "permlevel": 0,
   "precision": "",
   "print_hide": 0,
   "print_hide_if_no_value": 0,
   "print_width": null,
   "read_only": 0,
   "read_only_depends_on": null,
   "report_hide": 0,
   "reqd": 0,
   "search_index": 0,
   "translatable": 0,
   "unique": 0,
   "width": null
  },
  {
   "_assign": null,
   "_comments": null,
   "_liked_by": null,
   "_user_tags": null,
   "allow_in_quick_entry": 0,
   "allow_on_submit": 0,
   "bold": 0,
   "collapsible": 0,
   "collapsible_depends_on": null,
   "columns": 1,
   "creation": "2022-08-31 01:14:55.436034",
   "default": null,
   "depends_on": null,
   "description": null,
   "docstatus": 0,
   "dt": "Sales Invoice Item",
   "fetch_from": "item_code.no_of_pieces",
   "fetch_if_empty": 0,
   "fieldname": "no_of_pieces",
   "fieldtype": "Data",
   "hidden": 0,
   "hide_border": 0,
   "hide_days": 0,
   "hide_seconds": 0,
   "idx": 26,
   "ignore_user_permissions": 0,
   "ignore_xss_filter": 0,
   "in_global_search": 0,
   "in_list_view": 1,
   "in_preview": 0,
   "in_standard_filter": 0,
   "insert_after": "stock_qty",
   "is_system_generated": 0,
   "is_virtual": 0,
   "label": "No of Pieces",
   "length": 0,
   "mandatory_depends_on": null,
   "modified": "2022-08-31 01:14:55.436034",
   "modified_by": "Administrator",
   "module": null,
   "name": "Sales Invoice Item-no_of_pieces",
   "no_copy": 0,
   "non_negative": 0,
   "options": null,
   "owner": "Administrator",
   "permlevel": 0,
   "precision": "",
   "print_hide": 0,
   "print_hide_if_no_value": 0,
   "print_width": null,
   "read_only": 1,
   "read_only_depends_on": null,
   "report_hide": 0,
   "reqd": 0,
   "search_index": 0,
   "translatable": 0,
   "unique": 0,
   "width": null
  },
  {
   "_assign": null,
   "_comments": null,
   "_liked_by": null,
   "_user_tags": null,
   "allow_in_quick_entry": 0,
   "allow_on_submit": 0,
   "bold": 0,
   "collapsible": 0,
   "collapsible_depends_on": null,
   "columns": 0,
   "creation": "2022-09-26 20:27:16.613824",
   "default": null,
   "depends_on": null,
   "description": null,
   "docstatus": 0,
   "dt": "Sales Invoice Item",
   "fetch_from": "item_code.mrp_per_pcs",
   "fetch_if_empty": 0,
   "fieldname": "mrp_per_pcs",
   "fieldtype": "Currency",
   "hidden": 0,
   "hide_border": 0,
   "hide_days": 0,
   "hide_seconds": 0,
   "idx": 27,
   "ignore_user_permissions": 0,
   "ignore_xss_filter": 0,
   "in_global_search": 0,
   "in_list_view": 0,
   "in_preview": 0,
   "in_standard_filter": 0,
   "insert_after": "no_of_pieces",
   "is_system_generated": 0,
   "is_virtual": 0,
   "label": "MRP Per Pcs",
   "length": 0,
   "mandatory_depends_on": null,
   "modified": "2022-09-26 20:27:16.613824",
   "modified_by": "Administrator",
   "module": null,
   "name": "Sales Invoice Item-mrp_per_pcs",
   "no_copy": 0,
   "non_negative": 0,
   "options": null,
   "owner": "Administrator",
   "permlevel": 0,
   "precision": "",
   "print_hide": 0,
   "print_hide_if_no_value": 0,
   "print_width": null,
   "read_only": 0,
   "read_only_depends_on": null,
   "report_hide": 0,
   "reqd": 0,
   "search_index": 0,
   "translatable": 0,
   "unique": 0,
   "width": null
  },
  {
   "_assign": null,
   "_comments": null,
   "_liked_by": null,
   "_user_tags": null,
   "allow_in_quick_entry": 0,
   "allow_on_submit": 0,
   "bold": 0,
   "collapsible": 0,
   "collapsible_depends_on": null,
   "columns": 0,
   "creation": "2022-09-28 21:15:19.595859",
   "default": null,
   "depends_on": null,
   "description": null,
   "docstatus": 0,
   "dt": "Sales Invoice Item",
   "fetch_from": null,
   "fetch_if_empty": 0,
   "fieldname": "is_zero_rated",
   "fieldtype": "Check",
   "hidden": 0,
   "hide_border": 0,
   "hide_days": 0,
   "hide_seconds": 0,
   "idx": 11,
   "ignore_user_permissions": 0,
   "ignore_xss_filter": 0,
   "in_global_search": 0,
   "in_list_view": 0,
   "in_preview": 0,
   "in_standard_filter": 0,
   "insert_after": "sa_total_amount",
   "is_system_generated": 0,
   "is_virtual": 0,
   "label": "Is Zero Rated",
   "length": 0,
   "mandatory_depends_on": null,
   "modified": "2022-09-28 21:15:19.595859",
   "modified_by": "Administrator",
   "module": null,
   "name": "Sales Invoice Item-is_zero_rated",
   "no_copy": 0,
   "non_negative": 0,
   "options": null,
   "owner": "Administrator",
   "permlevel": 0,
   "precision": "",
   "print_hide": 0,
   "print_hide_if_no_value": 0,
   "print_width": null,
   "read_only": 0,
   "read_only_depends_on": null,
   "report_hide": 0,
   "reqd": 0,
   "search_index": 0,
   "translatable": 0,
   "unique": 0,
   "width": null
  },
  {
   "_assign": null,
   "_comments": null,
   "_liked_by": null,
   "_user_tags": null,
   "allow_in_quick_entry": 0,
   "allow_on_submit": 0,
   "bold": 0,
   "collapsible": 0,
   "collapsible_depends_on": null,
   "columns": 0,
   "creation": "2022-09-28 21:15:19.877717",
   "default": null,
   "depends_on": null,
   "description": null,
   "docstatus": 0,
   "dt": "Sales Invoice Item",
   "fetch_from": null,
   "fetch_if_empty": 0,
   "fieldname": "is_exempt",
   "fieldtype": "Check",
   "hidden": 0,
   "hide_border": 0,
   "hide_days": 0,
   "hide_seconds": 0,
   "idx": 12,
   "ignore_user_permissions": 0,
   "ignore_xss_filter": 0,
   "in_global_search": 0,
   "in_list_view": 0,
   "in_preview": 0,
   "in_standard_filter": 0,
   "insert_after": "is_zero_rated",
   "is_system_generated": 0,
   "is_virtual": 0,
   "label": "Is Exempt",
   "length": 0,
   "mandatory_depends_on": null,
   "modified": "2022-09-28 21:15:19.877717",
   "modified_by": "Administrator",
   "module": null,
   "name": "Sales Invoice Item-is_exempt",
   "no_copy": 0,
   "non_negative": 0,
   "options": null,
   "owner": "Administrator",
   "permlevel": 0,
   "precision": "",
   "print_hide": 0,
   "print_hide_if_no_value": 0,
   "print_width": null,
   "read_only": 0,
   "read_only_depends_on": null,
   "report_hide": 0,
   "reqd": 0,
   "search_index": 0,
   "translatable": 0,
   "unique": 0,
   "width": null
  },
  {
   "_assign": null,
   "_comments": null,
   "_liked_by": null,
   "_user_tags": null,
   "allow_in_quick_entry": 0,
   "allow_on_submit": 0,
   "bold": 0,
   "collapsible": 0,
   "collapsible_depends_on": null,
   "columns": 0,
   "creation": "2022-10-01 18:14:34.148592",
   "default": "18",
   "depends_on": null,
   "description": null,
   "docstatus": 0,
   "dt": "Sales Invoice Item",
   "fetch_from": null,
   "fetch_if_empty": 0,
   "fieldname": "sa_tax_rate",
   "fieldtype": "Data",
   "hidden": 0,
   "hide_border": 0,
   "hide_days": 0,
   "hide_seconds": 0,
   "idx": 8,
   "ignore_user_permissions": 0,
   "ignore_xss_filter": 0,
   "in_global_search": 0,
   "in_list_view": 0,
   "in_preview": 0,
   "in_standard_filter": 0,
   "insert_after": "description",
   "is_system_generated": 0,
   "is_virtual": 0,
   "label": "SA Tax Rate",
   "length": 0,
   "mandatory_depends_on": null,
   "modified": "2022-10-01 18:14:34.148592",
   "modified_by": "Administrator",
   "module": null,
   "name": "Sales Invoice Item-sa_tax_rate",
   "no_copy": 0,
   "non_negative": 0,
   "options": null,
   "owner": "Administrator",
   "permlevel": 0,
   "precision": "",
   "print_hide": 0,
   "print_hide_if_no_value": 0,
   "print_width": null,
   "read_only": 0,
   "read_only_depends_on": null,
   "report_hide": 0,
   "reqd": 0,
   "search_index": 0,
   "translatable": 0,
   "unique": 0,
   "width": null
  },
  {
   "_assign": null,
   "_comments": null,
   "_liked_by": null,
   "_user_tags": null,
   "allow_in_quick_entry": 0,
   "allow_on_submit": 0,
   "bold": 0,
   "collapsible": 0,
   "collapsible_depends_on": null,
   "columns": 0,
   "creation": "2022-11-22 20:04:22.901726",
   "default": null,
   "depends_on": null,
   "description": null,
   "docstatus": 0,
   "dt": "Sales Invoice Item",
   "fetch_from": null,
   "fetch_if_empty": 0,
   "fieldname": "sa_tax_amount",
   "fieldtype": "Data",
   "hidden": 0,
   "hide_border": 0,
   "hide_days": 0,
   "hide_seconds": 0,
   "idx": 9,
   "ignore_user_permissions": 0,
   "ignore_xss_filter": 0,
   "in_global_search": 0,
   "in_list_view": 0,
   "in_preview": 0,
   "in_standard_filter": 0,
   "insert_after": "sa_tax_rate",
   "is_system_generated": 0,
   "is_virtual": 0,
   "label": "SA Tax Amount",
   "length": 0,
   "mandatory_depends_on": null,
   "modified": "2022-11-22 20:04:22.901726",
   "modified_by": "Administrator",
   "module": null,
   "name": "Sales Invoice Item-sa_tax_amount",
   "no_copy": 0,
   "non_negative": 0,
   "options": null,
   "owner": "Administrator",
   "permlevel": 0,
   "precision": "",
   "print_hide": 0,
   "print_hide_if_no_value": 0,
   "print_width": null,
   "read_only": 0,
   "read_only_depends_on": null,
   "report_hide": 0,
   "reqd": 0,
   "search_index": 0,
   "translatable": 0,
   "unique": 0,
   "width": null
  },
  {
   "_assign": null,
   "_comments": null,
   "_liked_by": null,
   "_user_tags": null,
   "allow_in_quick_entry": 0,
   "allow_on_submit": 0,
   "bold": 0,
   "collapsible": 0,
   "collapsible_depends_on": null,
   "columns": 0,
   "creation": "2022-11-22 20:04:54.749999",
   "default": null,
   "depends_on": null,
   "description": null,
   "docstatus": 0,
   "dt": "Sales Invoice Item",
   "fetch_from": null,
   "fetch_if_empty": 0,
   "fieldname": "sa_total_amount",
   "fieldtype": "Currency",
   "hidden": 0,
   "hide_border": 0,
   "hide_days": 0,
   "hide_seconds": 0,
   "idx": 10,
   "ignore_user_permissions": 0,
   "ignore_xss_filter": 0,
   "in_global_search": 0,
   "in_list_view": 0,
   "in_preview": 0,
   "in_standard_filter": 0,
   "insert_after": "sa_tax_amount",
   "is_system_generated": 0,
   "is_virtual": 0,
   "label": "SA Total Amount",
   "length": 0,
   "mandatory_depends_on": null,
   "modified": "2022-11-22 20:04:54.749999",
   "modified_by": "Administrator",
   "module": null,
   "name": "Sales Invoice Item-sa_total_amount",
   "no_copy": 0,
   "non_negative": 0,
   "options": null,
   "owner": "Administrator",
   "permlevel": 0,
   "precision": "",
   "print_hide": 0,
   "print_hide_if_no_value": 0,
   "print_width": null,
   "read_only": 0,
   "read_only_depends_on": null,
   "report_hide": 0,
   "reqd": 0,
   "search_index": 0,
   "translatable": 0,
   "unique": 0,
   "width": null
  }
 ],
 "custom_perms": [],
 "doctype": "Sales Invoice Item",
 "links": [],
 "property_setters": [
  {
   "_assign": null,
   "_comments": null,
   "_liked_by": null,
   "_user_tags": null,
   "creation": "2023-03-24 19:38:45.387964",
   "default_value": null,
   "doc_type": "Sales Invoice Item",
   "docstatus": 0,
   "doctype_or_field": "DocField",
   "field_name": "rate",
   "idx": 0,
   "is_system_generated": 0,
   "modified": "2023-03-24 19:38:45.387964",
   "modified_by": "Administrator",
   "module": null,
   "name": "Sales Invoice Item-rate-read_only_depends_on",
   "owner": "Administrator",
   "property": "read_only_depends_on",
   "property_type": "Data",
   "row_name": null,
   "value": "eval:(doc.sub_group == \"STICK\" || doc.sub_group == \"CUP\" || doc.sub_group == \"1+1 OFFER\" || doc.sub_group == \"DUALS\" || doc.sub_group == \"TRUBAR\" || doc.sub_group == \"TUBS\")"
  },
  {
   "_assign": null,
   "_comments": null,
   "_liked_by": null,
   "_user_tags": null,
   "creation": "2023-02-11 12:56:30.617998",
   "default_value": null,
   "doc_type": "Sales Invoice Item",
   "docstatus": 0,
   "doctype_or_field": "DocField",
   "field_name": "target_warehouse",
   "idx": 0,
   "is_system_generated": 0,
   "modified": "2023-02-11 12:56:30.617998",
   "modified_by": "Administrator",
   "module": null,
   "name": "Sales Invoice Item-target_warehouse-hidden",
   "owner": "Administrator",
   "property": "hidden",
   "property_type": "Check",
   "row_name": null,
   "value": "1"
  },
  {
   "_assign": null,
   "_comments": null,
   "_liked_by": null,
   "_user_tags": null,
   "creation": "2023-02-11 12:56:30.127934",
   "default_value": null,
   "doc_type": "Sales Invoice Item",
   "docstatus": 0,
   "doctype_or_field": "DocField",
   "field_name": "barcode",
   "idx": 0,
   "is_system_generated": 1,
   "modified": "2023-02-11 12:56:30.127934",
   "modified_by": "Administrator",
   "module": null,
   "name": "Sales Invoice Item-barcode-hidden",
   "owner": "Administrator",
   "property": "hidden",
   "property_type": "Check",
   "row_name": null,
   "value": "0"
  },
  {
   "_assign": null,
   "_comments": null,
   "_liked_by": null,
   "_user_tags": null,
   "creation": "2023-02-07 14:19:44.874156",
   "default_value": null,
   "doc_type": "Sales Invoice Item",
   "docstatus": 0,
   "doctype_or_field": "DocField",
   "field_name": "item_group",
   "idx": 0,
   "is_system_generated": 0,
   "modified": "2023-02-07 14:19:44.874156",
   "modified_by": "Administrator",
   "module": null,
   "name": "Sales Invoice Item-item_group-hidden",
   "owner": "Administrator",
   "property": "hidden",
   "property_type": "Check",
   "row_name": null,
   "value": "0"
  },
  {
   "_assign": null,
   "_comments": null,
   "_liked_by": null,
   "_user_tags": null,
   "creation": "2023-02-07 13:36:18.251074",
   "default_value": null,
   "doc_type": "Sales Invoice Item",
   "docstatus": 0,
   "doctype_or_field": "DocField",
   "field_name": "serial_no",
   "idx": 0,
   "is_system_generated": 0,
   "modified": "2023-02-07 13:36:18.251074",
   "modified_by": "Administrator",
   "module": null,
   "name": "Sales Invoice Item-serial_no-in_list_view",
   "owner": "Administrator",
   "property": "in_list_view",
   "property_type": "Check",
   "row_name": null,
   "value": "0"
  },
  {
   "_assign": null,
   "_comments": null,
   "_liked_by": null,
   "_user_tags": null,
   "creation": "2023-02-07 13:36:18.164523",
   "default_value": null,
   "doc_type": "Sales Invoice Item",
   "docstatus": 0,
   "doctype_or_field": "DocField",
   "field_name": "batch_no",
   "idx": 0,
   "is_system_generated": 0,
   "modified": "2023-02-07 13:36:18.164523",
   "modified_by": "Administrator",
   "module": null,
   "name": "Sales Invoice Item-batch_no-in_list_view",
   "owner": "Administrator",
   "property": "in_list_view",
   "property_type": "Check",
   "row_name": null,
   "value": "0"
  },
  {
   "_assign": null,
   "_comments": null,
   "_liked_by": null,
   "_user_tags": null,
   "creation": "2023-02-07 13:36:18.075854",
   "default_value": null,
   "doc_type": "Sales Invoice Item",
   "docstatus": 0,
   "doctype_or_field": "DocField",
   "field_name": "warehouse",
   "idx": 0,
   "is_system_generated": 0,
   "modified": "2023-02-07 13:36:18.075854",
   "modified_by": "Administrator",
   "module": null,
   "name": "Sales Invoice Item-warehouse-in_list_view",
   "owner": "Administrator",
   "property": "in_list_view",
   "property_type": "Check",
   "row_name": null,
   "value": "0"
  },
  {
   "_assign": null,
   "_comments": null,
   "_liked_by": null,
   "_user_tags": null,
   "creation": "2023-02-07 13:36:17.953103",
   "default_value": null,
   "doc_type": "Sales Invoice Item",
   "docstatus": 0,
   "doctype_or_field": "DocField",
   "field_name": "item_code",
   "idx": 0,
   "is_system_generated": 0,
   "modified": "2023-02-07 13:36:17.953103",
   "modified_by": "Administrator",
   "module": null,
   "name": "Sales Invoice Item-item_code-columns",
   "owner": "Administrator",
   "property": "columns",
   "property_type": "Int",
   "row_name": null,
   "value": "2"
  },
  {
   "_assign": null,
   "_comments": null,
   "_liked_by": null,
   "_user_tags": null,
   "creation": "2023-02-07 13:28:16.676858",
   "default_value": null,
   "doc_type": "Sales Invoice Item",
   "docstatus": 0,
   "doctype_or_field": "DocField",
   "field_name": "actual_qty",
   "idx": 0,
   "is_system_generated": 0,
   "modified": "2023-02-07 13:28:16.676858",
   "modified_by": "Administrator",
   "module": null,
   "name": "Sales Invoice Item-actual_qty-columns",
   "owner": "Administrator",
   "property": "columns",
   "property_type": "Int",
   "row_name": null,
   "value": "1"
  },
  {
   "_assign": null,
   "_comments": null,
   "_liked_by": null,
   "_user_tags": null,
   "creation": "2023-02-07 13:28:16.595156",
   "default_value": null,
   "doc_type": "Sales Invoice Item",
   "docstatus": 0,
   "doctype_or_field": "DocField",
   "field_name": "actual_qty",
   "idx": 0,
   "is_system_generated": 0,
   "modified": "2023-02-07 13:28:16.595156",
   "modified_by": "Administrator",
   "module": null,
   "name": "Sales Invoice Item-actual_qty-in_list_view",
   "owner": "Administrator",
   "property": "in_list_view",
   "property_type": "Check",
   "row_name": null,
   "value": "1"
  },
  {
   "_assign": null,
   "_comments": null,
   "_liked_by": null,
   "_user_tags": null,
   "creation": "2023-02-07 13:28:16.463411",
   "default_value": null,
   "doc_type": "Sales Invoice Item",
   "docstatus": 0,
   "doctype_or_field": "DocField",
   "field_name": "amount",
   "idx": 0,
   "is_system_generated": 0,
   "modified": "2023-02-07 13:28:16.463411",
   "modified_by": "Administrator",
   "module": null,
   "name": "Sales Invoice Item-amount-columns",
   "owner": "Administrator",
   "property": "columns",
   "property_type": "Int",
   "row_name": null,
   "value": "1"
  },
  {
   "_assign": null,
   "_comments": null,
   "_liked_by": null,
   "_user_tags": null,
   "creation": "2022-09-28 12:29:10.178189",
   "default_value": null,
   "doc_type": "Sales Invoice Item",
   "docstatus": 0,
   "doctype_or_field": "DocField",
   "field_name": "discount_account",
   "idx": 0,
   "is_system_generated": 0,
   "modified": "2022-09-28 12:29:10.178189",
   "modified_by": "Administrator",
   "module": null,
   "name": "Sales Invoice Item-discount_account-mandatory_depends_on",
   "owner": "Administrator",
   "property": "mandatory_depends_on",
   "property_type": "Code",
   "row_name": null,
   "value": ""
  },
  {
   "_assign": null,
   "_comments": null,
   "_liked_by": null,
   "_user_tags": null,
   "creation": "2022-09-28 12:29:10.140838",
   "default_value": null,
   "doc_type": "Sales Invoice Item",
   "docstatus": 0,
   "doctype_or_field": "DocField",
   "field_name": "discount_account",
   "idx": 0,
   "is_system_generated": 0,
   "modified": "2022-09-28 12:29:10.140838",
   "modified_by": "Administrator",
   "module": null,
   "name": "Sales Invoice Item-discount_account-hidden",
   "owner": "Administrator",
   "property": "hidden",
   "property_type": "Check",
   "row_name": null,
   "value": "1"
  },
  {
   "_assign": null,
   "_comments": null,
   "_liked_by": null,
   "_user_tags": null,
   "creation": "2022-09-04 17:35:38.402058",
   "default_value": null,
   "doc_type": "Sales Invoice Item",
   "docstatus": 0,
   "doctype_or_field": "DocField",
   "field_name": "section_break_21",
   "idx": 0,
   "is_system_generated": 0,
   "modified": "2022-09-04 17:35:38.402058",
   "modified_by": "Administrator",
   "module": null,
   "name": "Sales Invoice Item-section_break_21-hidden",
   "owner": "Administrator",
   "property": "hidden",
   "property_type": "Check",
   "row_name": null,
   "value": "1"
  },
  {
   "_assign": null,
   "_comments": null,
   "_liked_by": null,
   "_user_tags": null,
   "creation": "2022-09-04 17:35:38.332508",
   "default_value": null,
   "doc_type": "Sales Invoice Item",
   "docstatus": 0,
   "doctype_or_field": "DocField",
   "field_name": "grant_commission",
   "idx": 0,
   "is_system_generated": 0,
   "modified": "2022-09-04 17:35:38.332508",
   "modified_by": "Administrator",
   "module": null,
   "name": "Sales Invoice Item-grant_commission-hidden",
   "owner": "Administrator",
   "property": "hidden",
   "property_type": "Check",
   "row_name": null,
   "value": "1"
  },
  {
   "_assign": null,
   "_comments": null,
   "_liked_by": null,
   "_user_tags": null,
   "creation": "2022-09-04 17:35:38.222401",
   "default_value": null,
   "doc_type": "Sales Invoice Item",
   "docstatus": 0,
   "doctype_or_field": "DocField",
   "field_name": "is_free_item",
   "idx": 0,
   "is_system_generated": 0,
   "modified": "2022-09-04 17:35:38.222401",
   "modified_by": "Administrator",
   "module": null,
   "name": "Sales Invoice Item-is_free_item-hidden",
   "owner": "Administrator",
   "property": "hidden",
   "property_type": "Check",
   "row_name": null,
   "value": "1"
  },
  {
   "_assign": null,
   "_comments": null,
   "_liked_by": null,
   "_user_tags": null,
   "creation": "2022-09-04 17:34:26.049341",
   "default_value": null,
   "doc_type": "Sales Invoice Item",
   "docstatus": 0,
   "doctype_or_field": "DocField",
   "field_name": "section_break_54",
   "idx": 0,
   "is_system_generated": 0,
   "modified": "2022-09-04 17:34:26.049341",
   "modified_by": "Administrator",
   "module": null,
   "name": "Sales Invoice Item-section_break_54-hidden",
   "owner": "Administrator",
   "property": "hidden",
   "property_type": "Check",
   "row_name": null,
   "value": "1"
  },
  {
   "_assign": null,
   "_comments": null,
   "_liked_by": null,
   "_user_tags": null,
   "creation": "2022-09-04 17:34:25.965519",
   "default_value": null,
   "doc_type": "Sales Invoice Item",
   "docstatus": 0,
   "doctype_or_field": "DocField",
   "field_name": "accounting_dimensions_section",
   "idx": 0,
   "is_system_generated": 0,
   "modified": "2022-09-04 17:34:25.965519",
   "modified_by": "Administrator",
   "module": null,
   "name": "Sales Invoice Item-accounting_dimensions_section-hidden",
   "owner": "Administrator",
   "property": "hidden",
   "property_type": "Check",
   "row_name": null,
   "value": "1"
  },
  {
   "_assign": null,
   "_comments": null,
   "_liked_by": null,
   "_user_tags": null,
   "creation": "2022-09-04 17:34:25.717887",
   "default_value": null,
   "doc_type": "Sales Invoice Item",
   "docstatus": 0,
   "doctype_or_field": "DocField",
   "field_name": "section_break_18",
   "idx": 0,
   "is_system_generated": 0,
   "modified": "2022-09-04 17:34:25.717887",
   "modified_by": "Administrator",
   "module": null,
   "name": "Sales Invoice Item-section_break_18-hidden",
   "owner": "Administrator",
   "property": "hidden",
   "property_type": "Check",
   "row_name": null,
   "value": "1"
  },
  {
   "_assign": null,
   "_comments": null,
   "_liked_by": null,
   "_user_tags": null,
   "creation": "2022-09-04 17:34:25.634471",
   "default_value": null,
   "doc_type": "Sales Invoice Item",
   "docstatus": 0,
   "doctype_or_field": "DocField",
   "field_name": "deferred_revenue",
   "idx": 0,
   "is_system_generated": 0,
   "modified": "2022-09-04 17:34:25.634471",
   "modified_by": "Administrator",
   "module": null,
   "name": "Sales Invoice Item-deferred_revenue-hidden",
   "owner": "Administrator",
   "property": "hidden",
   "property_type": "Check",
   "row_name": null,
   "value": "1"
  },
  {
   "_assign": null,
   "_comments": null,
   "_liked_by": null,
   "_user_tags": null,
   "creation": "2022-09-04 17:34:25.551859",
   "default_value": null,
   "doc_type": "Sales Invoice Item",
   "docstatus": 0,
   "doctype_or_field": "DocField",
   "field_name": "accounting",
   "idx": 0,
   "is_system_generated": 0,
   "modified": "2022-09-04 17:34:25.551859",
   "modified_by": "Administrator",
   "module": null,
   "name": "Sales Invoice Item-accounting-hidden",
   "owner": "Administrator",
   "property": "hidden",
   "property_type": "Check",
   "row_name": null,
   "value": "1"
  },
  {
   "_assign": null,
   "_comments": null,
   "_liked_by": null,
   "_user_tags": null,
   "creation": "2022-09-04 17:34:25.471361",
   "default_value": null,
   "doc_type": "Sales Invoice Item",
   "docstatus": 0,
   "doctype_or_field": "DocField",
   "field_name": "drop_ship",
   "idx": 0,
   "is_system_generated": 0,
   "modified": "2022-09-04 17:34:25.471361",
   "modified_by": "Administrator",
   "module": null,
   "name": "Sales Invoice Item-drop_ship-hidden",
   "owner": "Administrator",
   "property": "hidden",
   "property_type": "Check",
   "row_name": null,
   "value": "1"
  },
  {
   "_assign": null,
   "_comments": null,
   "_liked_by": null,
   "_user_tags": null,
   "creation": "2022-09-04 17:34:25.385549",
   "default_value": null,
   "doc_type": "Sales Invoice Item",
   "docstatus": 0,
   "doctype_or_field": "DocField",
   "field_name": "item_tax_template",
   "idx": 0,
   "is_system_generated": 0,
   "modified": "2022-09-04 17:34:25.385549",
   "modified_by": "Administrator",
   "module": null,
   "name": "Sales Invoice Item-item_tax_template-read_only",
   "owner": "Administrator",
   "property": "read_only",
   "property_type": "Check",
   "row_name": null,
   "value": "1"
  },
  {
   "_assign": null,
   "_comments": null,
   "_liked_by": null,
   "_user_tags": null,
   "creation": "2022-09-04 17:34:25.270325",
   "default_value": null,
   "doc_type": "Sales Invoice Item",
   "docstatus": 0,
   "doctype_or_field": "DocField",
   "field_name": "image_section",
   "idx": 0,
   "is_system_generated": 0,
   "modified": "2022-09-04 17:34:25.270325",
   "modified_by": "Administrator",
   "module": null,
   "name": "Sales Invoice Item-image_section-hidden",
   "owner": "Administrator",
   "property": "hidden",
   "property_type": "Check",
   "row_name": null,
   "value": "1"
  },
  {
   "_assign": null,
   "_comments": null,
   "_liked_by": null,
   "_user_tags": null,
   "creation": "2022-08-31 01:14:55.119409",
   "default_value": null,
   "doc_type": "Sales Invoice Item",
   "docstatus": 0,
   "doctype_or_field": "DocField",
   "field_name": "rate",
   "idx": 0,
   "is_system_generated": 0,
   "modified": "2022-08-31 01:14:55.119409",
   "modified_by": "Administrator",
   "module": null,
   "name": "Sales Invoice Item-rate-columns",
   "owner": "Administrator",
   "property": "columns",
   "property_type": "Int",
   "row_name": null,
   "value": "1"
  },
  {
   "_assign": null,
   "_comments": null,
   "_liked_by": null,
   "_user_tags": null,
   "creation": "2022-08-31 01:14:54.954488",
   "default_value": null,
   "doc_type": "Sales Invoice Item",
   "docstatus": 0,
   "doctype_or_field": "DocField",
   "field_name": "uom",
   "idx": 0,
   "is_system_generated": 0,
   "modified": "2022-08-31 01:14:54.954488",
   "modified_by": "Administrator",
   "module": null,
   "name": "Sales Invoice Item-uom-columns",
   "owner": "Administrator",
   "property": "columns",
   "property_type": "Int",
   "row_name": null,
   "value": "1"
  },
  {
   "_assign": null,
   "_comments": null,
   "_liked_by": null,
   "_user_tags": null,
   "creation": "2022-08-31 01:14:54.879513",
   "default_value": null,
   "doc_type": "Sales Invoice Item",
   "docstatus": 0,
   "doctype_or_field": "DocField",
   "field_name": "uom",
   "idx": 0,
   "is_system_generated": 0,
   "modified": "2022-08-31 01:14:54.879513",
   "modified_by": "Administrator",
   "module": null,
   "name": "Sales Invoice Item-uom-in_list_view",
   "owner": "Administrator",
   "property": "in_list_view",
   "property_type": "Check",
   "row_name": null,
   "value": "1"
  },
  {
   "_assign": null,
   "_comments": null,
   "_liked_by": null,
   "_user_tags": null,
   "creation": "2022-08-31 01:14:54.801263",
   "default_value": null,
   "doc_type": "Sales Invoice Item",
   "docstatus": 0,
   "doctype_or_field": "DocField",
   "field_name": "qty",
   "idx": 0,
   "is_system_generated": 0,
   "modified": "2022-08-31 01:14:54.801263",
   "modified_by": "Administrator",
   "module": null,
   "name": "Sales Invoice Item-qty-columns",
   "owner": "Administrator",
   "property": "columns",
   "property_type": "Int",
   "row_name": null,
   "value": "1"
  },
  {
   "_assign": null,
   "_comments": null,
   "_liked_by": null,
   "_user_tags": null,
   "creation": "2022-08-31 01:14:54.723740",
   "default_value": null,
   "doc_type": "Sales Invoice Item",
   "docstatus": 0,
   "doctype_or_field": "DocField",
   "field_name": "item_name",
   "idx": 0,
   "is_system_generated": 0,
   "modified": "2022-08-31 01:14:54.723740",
   "modified_by": "Administrator",
   "module": null,
   "name": "Sales Invoice Item-item_name-columns",
   "owner": "Administrator",
   "property": "columns",
   "property_type": "Int",
   "row_name": null,
   "value": "2"
  },
  {
   "_assign": null,
   "_comments": null,
   "_liked_by": null,
   "_user_tags": null,
   "creation": "2022-08-31 01:14:54.646818",
   "default_value": null,
   "doc_type": "Sales Invoice Item",
   "docstatus": 0,
   "doctype_or_field": "DocField",
   "field_name": "item_name",
   "idx": 0,
   "is_system_generated": 0,
   "modified": "2022-08-31 01:14:54.646818",
   "modified_by": "Administrator",
   "module": null,
   "name": "Sales Invoice Item-item_name-in_list_view",
   "owner": "Administrator",
   "property": "in_list_view",
   "property_type": "Check",
   "row_name": null,
   "value": "1"
  }
 ],
 "sync_on_migrate": 1
}